{
  "infrastructure": {
    "category": "infrastructure",
    "producedBy": "operator",
    "timestamp": "2026-03-12T18:31:00Z",
    "title": "Infrastructure Status",
    "body": "# Infrastructure Status\n\n## Overall Health\nHEALTHY\n\n## Collectors\n| ID | Type | Symbol | Timeframe | Disabled | Data Fresh | Priority | Notes |\n|----|------|--------|-----------|----------|------------|----------|-------|\n| `[[collector/e5125995]]` | alpaca | GLD | 5min | No | ✅ 18:15Z ($469.05) | IMPORTANT | 10 active tasks + feeds promotion candidate `[[model/54b33aea]]` |\n| `[[collector/9c3ba4ef]]` | alpaca | XLE | 5min | No | ✅ 18:15Z ($57.89) | IMPORTANT | 2 active tasks |\n| `[[collector/c00fd831]]` | alpaca | AAPL | 5min | No | ✅ 18:15Z ($255.55) | IMPORTANT | 1 active task |\n| `[[collector/ab739989]]` | alpaca | ESTC | 5min | No | ✅ 18:15Z ($52.01) | IMPORTANT | 2 active tasks |\n| `[[collector/35cf414b]]` | alpaca | ESTC | 15min | No | ✅ 18:15Z ($52.00) | IMPORTANT | Paired with ESTC 5min collector |\n| `[[collector/2a8681ef]]` | alpaca | SLV | 5min | No | ✅ 18:15Z ($76.94) | LOW | No active tasks |\n| `[[collector/3d04a943]]` | alpaca | NVDA | 5min | No | ✅ 18:15Z ($183.53) | LOW | No active tasks |\n| `[[collector/999b208d]]` | alpaca | SPY | 5min | No | ✅ 18:15Z ($668.25) | LOW | No active tasks |\n| `[[collector/9c417caa]]` | alpaca | QQQ | 5min | No | ✅ 18:15Z ($599.31) | LOW | No active tasks |\n| `[[collector/f60d4dce]]` | alpaca | IWM | 5min | No | ✅ 18:15Z ($248.86) | LOW | No active tasks |\n\nAll 10 collectors enabled and producing data with no gaps during market hours. Checked 16:30-18:15Z window: 22 consecutive 5min candles for all instruments. ESTC 15min: 10 candles in 2.5h window.\n\n## Brokers\n| ID | Name | Type | Status | Notes |\n|----|------|------|--------|-------|\n| `[[broker/ed622468]]` | Alpaca Paper | alpaca | ✅ Configured | paper-api.alpaca.markets, SIP data feed. Linked to `[[portfolio/paper-alpha-01]]` via pb `81234300`. |\n\n## Active Tasks (15 enabled)\n| Instrument | Active Tasks | Collectors |\n|------------|-------------|------------|\n| GLD | 10 | `[[collector/e5125995]]` |\n| XLE | 2 | `[[collector/9c3ba4ef]]` |\n| ESTC | 2 | `[[collector/ab739989]]`, `[[collector/35cf414b]]` |\n| AAPL | 1 | `[[collector/c00fd831]]` |\n\n## Portfolio Status\n| Portfolio | Models | Broker | Status |\n|-----------|--------|--------|--------|\n| `[[portfolio/paper-alpha-01]]` | 0 (empty) | `[[broker/ed622468]]` (Alpaca Paper) | Idle — no live trading |\n\n**Note:** `[[model/54b33aea]]` at 4/5 consecutive ≥0.80 — if promoted ~Mar 13, GLD collector and Alpaca Paper broker become CRITICAL priority.\n\n## Active Issues\n*None*\n\n## Resolved Issues (last 7 days)\n*None*"
  },
  "model-rankings": {
    "category": "model-rankings",
    "producedBy": "analyst",
    "timestamp": "2026-03-12T18:00:00Z",
    "title": "Model Rankings",
    "body": "# Model Rankings\n\n## ⚠️ HEADLINE: Multi-Horizon Analysis Reveals 54b33aea Degradation — Promotion HELD\n\nFirst comprehensive multi-horizon evaluation across all key models. The 16w scores that dominated previous rankings are **masking a GLD regime shift**. All GLD models show weak 4w/8w performance. `[[model/54b33aea]]`'s 30-day OOS validation FAILED (score 0.29 vs 16w 0.83, 65% deviation — well outside 15% tolerance).\n\n**No models currently pass full multi-horizon promotion criteria.** The pipeline is NOT empty — 54b33aea remains at 4/5 consecutive 16w ≥0.80 — but promotion requires recent performance recovery.\n\n## Ready for Promotion\n| Rank | Model | Task | Score | Sharpe | MaxDD | Expectancy | Ops | WinRate | Backtest | Recommendation |\n|------|-------|------|-------|--------|-------|------------|-----|---------|----------|----------------|\n| *(none)* | — | — | — | — | — | — | — | — | — | No models pass multi-horizon validation |\n\n## Promotion Pipeline (Held — Require Multi-Horizon Confirmation)\n\n### `[[model/54b33aea]]` — PIPELINE LEADER — 4/5 CONSECUTIVE ≥0.80 — **PROMOTION HELD**\n\n| Horizon | Score | Trend | Assessment |\n|---------|-------|-------|------------|\n| **16w** | **0.8308** | Stable (4/5 ≥0.80) | ✅ Looks great on surface |\n| **OOS expanding** | **0.8071** ↓ | Declining (0.811→0.811→0.807) | ⚠️ First decline |\n| **8w** | **0.6588** ↓ | Declining (0.756→0.662→0.659) | ❌ Significant drop |\n| **4w** | **0.2976** | Flat/weak (0.287→0.288→0.298) | ❌ Terrible |\n| **1w** | **0.0849** | Rising from zero | ❌ Near-zero signal |\n\n**30-Day OOS Validation (Feb 10 — Mar 12) — FAILED:**\n| Metric | 16w Stored | 30-Day Backtest | Change |\n|--------|-----------|-----------------|--------|\n| Score | 0.8308 | **0.2908** | **-65%** |\n| cecpp | 0.8915 | **0.4359** | **-51%** |\n| Sharpe | 11.06 | **0.97** | **-91%** |\n| Expectancy | $17.72 | **$2.90** | **-84%** |\n| WR | ~94% | **57.9%** (11W/8L) | Degraded |\n| DD | 9.05% | 4.37% | Better (less activity) |\n\n**IS Backtest (confirmed):** Score 0.703, DD 13.38% ✅, 244 ops, WR 66.7%, cecpp 0.908\n\n**Assessment:** The 16w score is buoyed by strong early OOS data (Dec 2025 — Jan 2026). As that data rolls off the window, the 16w will converge toward the 8w level (~0.66). **Even if eval 5 (Mar 13) shows ≥0.80, I will NOT recommend promotion** until short-horizon recovery is demonstrated.\n\n### `[[model/4fc2c04e]]` 🏆 — STRONGEST ACROSS ALL HORIZONS — IS DD BLOCKED\n\n| Horizon | Score | Trend |\n|---------|-------|-------|\n| **16w** | **0.8557** | Stable (5/5 consecutive) |\n| **8w** | **0.8302** ↑ | Climbing (0.771→0.790→0.830) |\n| **4w** | **0.6068** ↑ | Climbing fast (0.311→0.404→0.607) |\n\n**IS DD: 18.35% ❌ — permanently blocked.** This is the model that SHOULD be promoted — it's the only one thriving in the current regime. But IS risk ceiling is too high.\n\n## GLD Regime Analysis — All Models Affected\n\n| Model | Task | 16w Score | 8w Score | 4w Score | 4w Ops | 4w Profit | 4w Status |\n|-------|------|-----------|----------|----------|--------|-----------|-----------|\n| `[[model/4fc2c04e]]` | EXP-11 | 0.857 | **0.830 ↑** | **0.607 ↑** | 14 | $56 | ⭐ Exception |\n| `[[model/54b33aea]]` | EXP-14 | 0.831 | 0.659 ↓ | 0.298 | 27 | $64 | Weak |\n| `[[model/001b9ef2]]` | EXP-20 | 0.750 | 0.541 ↑ | 0.311 | 26 | $56 | Weak |\n| `[[model/fd60312c]]` | EXP-17 | 0.743 | 0.510 ↑ | 0.238 | 23 | $31 | Weak |\n| `[[model/198d0c1f]]` | EXP-15 | 0.806 | 0.396 ↑ | 0.062 | 6 | $0 | ❌ Near-dead |\n| `[[model/289705b1]]` | EXP-15 | 0.804 | — | — | 6 | $0 | ❌ Near-dead |\n| `[[model/61694274]]` | EXP-10 | 0.783 | 0.465 ↓ | 0.034 | 5 | $0 | ❌ Dead |\n\n**Conclusion:** The last 4 weeks have been very challenging for GLD models. Only `[[model/4fc2c04e]]` (EXP-11 tuned scorer) is thriving. The regime may shift back, or these models may be entering a permanent signal decay phase.\n\n## Track C — Bouncing (Reset to 1/5)\n| Model | Task | 16w Score | 8w | 4w | IS DD | Consec ≥0.80 | Status |\n|-------|------|-----------|-----|-----|-------|--------------|--------|\n| `[[model/198d0c1f]]` | `[[task/32062f72]]` EXP-15 | 0.8064 ↑ | 0.396 | 0.062 | 13.38% ✅ | 1/5 (Mar 11 broke) | 4w near-zero ⚠️ |\n| `[[model/289705b1]]` | `[[task/32062f72]]` EXP-15 | 0.8036 ↑ | — | — | 13.38% ✅ | 1/5 (Mar 11 broke) | Same pattern |\n\n**Assessment:** Bounced back above 0.80 on 16w but 4w shows near-zero activity ($0 profit). These models may also be living on stale data.\n\n## Monitoring (Promising — Emerging Safety Track)\n| Model | Task | 16w Score | 8w Score | 4w Score | IS DD | Evals | Trend |\n|-------|------|-----------|----------|----------|-------|-------|-------|\n| `[[model/99f035df]]` 🆕 | `[[task/eb1b1e97]]` (EXP-20) | **0.7902** | — | — | TBD | 1 | NEW — near threshold! |\n| `[[model/001b9ef2]]` ⭐ | `[[task/eb1b1e97]]` (EXP-20) | 0.7503 ↑ | 0.5408 ↑ | 0.3106 ↑ | 8.93% ⭐ | 2 | Climbing ~2.0pp/eval |\n| `[[model/fd60312c]]` ⭐ | `[[task/e3017490]]` (EXP-17) | 0.7426 ↑ | 0.5099 ↑ | 0.2377 | 8.34% ⭐⭐ | 2 | Climbing ~2.5pp/eval |\n| `[[model/2d5307c8]]` | `[[task/8b877f86]]` (EXP-21) | 0.7081 ↑ | — | — | 9.79% ✅ | 2 | Climbing ~2.6pp/eval |\n| `[[model/f601bbb5]]` | `[[task/eb61f98b]]` (EXP-22) | 0.7039 | — | — | 8.93% ⭐ | 1 | First eval |\n| `[[model/3218f580]]` | `[[task/03255fc1]]` (EXP-23) | 0.6635 | — | — | 7.13% ⭐⭐⭐ | 1 | CLIFF JUMP (trade_count_factor) |\n| `[[model/977e04dd]]` | `[[task/e3017490]]` (EXP-17) | 0.6120 ↑ | — | — | 8.43% ⭐⭐ | 2 | Climbing ~2.2pp/eval |\n| `[[model/7376e292]]` 🆕 | `[[task/eb61f98b]]` (EXP-22) | — | — | — | TBD | 0 | First eval Mar 13 |\n| `[[model/df006105]]` 🆕 | `[[task/03255fc1]]` (EXP-23) | — | — | — | TBD | 0 | First eval Mar 13 |\n\n**⚠️ Caution on emerging track:** While 16w scores are climbing, the 4w scores for 001b9ef2 (0.31) and fd60312c (0.24) are also weak. Their 16w climb may plateau as the current regime dominates the window.\n\n## Volatile / IS DD Blocked\n| Model | Task | 16w Score | IS DD | Status |\n|-------|------|-----------|-------|--------|\n| `[[model/7f7ac2e4]]` | EXP-11 | 0.7976 | 14.03% ⚠️ | 4w: 9 ops, $121 — decent recent. IS DD borderline. |\n| `[[model/50c0ac0b]]` | EXP-14 | 0.8130 | **19.27% ❌** | Permanently blocked |\n| `[[model/6e5c665f]]` | EXP-15 | 0.7709 ↓ | **19.20% ❌** | Blocked + declining |\n\n## Degrading (Action Needed)\n| Model | Task | 16w Score | 16w Trend | 8w | 4w | Live? | Recommendation |\n|-------|------|-----------|-----------|-----|-----|-------|----------------|\n| `[[model/61694274]]` ↓↓ | EXP-10 | 0.7833 ↓ | 0.833→0.827→0.806→0.793→**0.783** | 0.465 | 0.034 | No | 6 consecutive declines. 4w dead. FAILED. |\n| `[[model/c9647008]]` | EXP-15 | ~0.659 | Stable low | — | — | No | Below demotion threshold. |\n| `[[model/64a144a1]]` | EXP-13 ESTC | 0.516 ↓ | Declining | — | — | No | ESTC deadline Mar 15. |\n\n## New Models This Cycle (7 new since 12:30Z)\n| Model | Task | Creation Score | Assessment |\n|-------|------|---------------|------------|\n| `[[model/7376e292]]` | `[[task/eb61f98b]]` (EXP-22) | 0.759 | Strong debut. First 16w eval Mar 13. |\n| `[[model/df006105]]` | `[[task/03255fc1]]` (EXP-23) | 0.615 | cecpp-scorer model. First eval Mar 13. |\n| `[[model/a641b9dc]]` | `[[task/8ee183d8]]` (EXP-25) | 0.211 | EXP-25 debut. Very early. |\n| `[[model/fbc003f2]]` | `[[task/8ee183d8]]` (EXP-25) | 0.123 | Very early. |\n| `[[model/2fd165d3]]` | `[[task/8ee183d8]]` (EXP-25) | 0.030 | Very early. |\n| `[[model/2bbc5231]]` | `[[task/9ac8eba0]]` (EXP-18) | 0.616 | Walk-forward. |\n| `[[model/537947eb]]` | `[[task/98dd3981]]` (EXP-19 AAPL) | 0.360 | Weak. |\n\n## Summary\n- **Total models surveyed**: 97+\n- **Above 16w promotion threshold (≥0.80)**: 8\n- **Pass multi-horizon validation**: **0** ⚠️\n- **Promotion candidates held**: 1 (54b33aea — OOS validation failed)\n- **Permanently blocked (IS DD)**: 3 (4fc2c04e, 50c0ac0b, 6e5c665f)\n- **Degrading models**: 3 (61694274, c9647008, 64a144a1)\n- **Emerging with potential**: 7 (001b9ef2, fd60312c, 2d5307c8, f601bbb5, 977e04dd, 99f035df, 7376e292)\n- **New this cycle**: 7 models\n\n## Methodology Change (Effective This Cycle)\n**Promotion now requires multi-horizon confirmation:**\n1. 16w score ≥ 0.80 for 5+ consecutive evaluations (unchanged)\n2. **NEW: 8w score ≥ 0.60** (ensures recent 2-month performance is adequate)\n3. **NEW: 4w score ≥ 0.40** (ensures recent 1-month performance is not dead)\n4. **NEW: 30-day OOS validation within 30% of 16w score** (relaxed from strict 15%)\n5. IS DD < 15% (unchanged)\n\n## Promotion Timeline\n| Scenario | Model(s) | Earliest | Probability | Dependency |\n|----------|----------|----------|-------------|------------|\n| 54b33aea recovers short horizons | `[[model/54b33aea]]` | **Mar 17+** | **20%** | Needs 4w/8w to recover + backtest validation |\n| Emerging safety reaches threshold | `[[model/001b9ef2]]`/`[[model/fd60312c]]` | **Mar 25+** | **25%** | Reach 0.80 + 5 evals + multi-horizon OK |\n| 99f035df fast track | `[[model/99f035df]]` | **Mar 20+** | **15%** | Already at 0.79 — needs 5 evals |\n| Track C sustains | `[[model/198d0c1f]]`/`[[model/289705b1]]` | Mar 20+ | **10%** | 4w near-zero is a problem |\n| No promotion by Mar 20 | — | — | **30%** | Current GLD regime persists |"
  },
  "portfolio-status": {
    "category": "portfolio-status",
    "producedBy": "portfolio-manager",
    "timestamp": "2026-03-12T10:00:00Z",
    "title": "Portfolio Status",
    "body": "# Portfolio Status\n\n## Portfolios\n| Portfolio | Models (enabled/total) | Total Allocation | Broker |\n|-----------|----------------------|------------------|--------|\n| `[[portfolio/paper-alpha-01]]` | 0/0 | 0% | Alpaca Paper (`[[broker/alpaca-paper]]`) |\n\n## Active Models\n| Portfolio | Model | Allocation | Enabled Since | Score | Sharpe | MaxDD | Expectancy | Orders (24h) | Status |\n|-----------|-------|------------|---------------|-------|--------|-------|------------|--------------|--------|\n| *(none — no models in portfolio yet)* | — | — | — | — | — | — | — | — | — |\n\n## Pipeline Summary\n\n### ⭐ Promotion Candidate — 54b33aea at 4/5 CONSECUTIVE ≥0.80\n| Model | Task | Score (16w) | Eval Trajectory | Sharpe | DD (OOS) | DD (IS) | cecpp | Expectancy | Ops | Consecutive ≥0.80 |\n|-------|------|------------|-----------------|--------|----------|---------|-------|------------|-----|--------------------|\n| `[[model/54b33aea]]` | `[[task/1d615d47]]` (EXP-14) | **0.8308** | 0.811→0.832→0.833→**0.831** | 11.06 | 9.05% | 13.38% ✅ | 0.8915 | $17.72 | 61 | **4/5** ⭐⭐⭐⭐ |\n\n**Promotion eval: Mar 13 ~02:15Z.** If score ≥0.80 → 5/5 → PROMOTE to `[[portfolio/paper-alpha-01]]` at 5% allocation.\nAnalyst has pre-approved promotion at 5/5.\n\n### Track C — Bouncing (1/5)\n| Model | Score | Previous | Ops | DD | Consecutive ≥0.80 |\n|-------|-------|----------|-----|-----|-----|\n| `[[model/198d0c1f]]` | **0.8064** ↑ | 0.7972 | 50 (+6) | 9.44% | 1/5 |\n| `[[model/289705b1]]` | **0.8036** ↑ | 0.7937 | 49 (+6) | 9.44% | 1/5 |\n\n### Track B — Declining (0/5)\n| Model | Score | Previous | Consecutive ≥0.80 |\n|-------|-------|----------|-----|\n| `[[model/61694274]]` | 0.7833 ↓ | 0.7929 | 0/5 |\n| `[[model/2704110c]]` | 0.7833 ↓ | 0.7928 | 0/5 |\n\n### Track A — Recovering (0/5)\n| Model | Score | Previous | Consecutive ≥0.80 |\n|-------|-------|----------|-----|\n| `[[model/7f7ac2e4]]` | 0.7976 ↑ | 0.7874 | 0/5 |\n\n### Emerging Safety Track\n| Model | Score | IS DD | Trend | ETA 0.80 |\n|-------|-------|-------|-------|----------|\n| `[[model/fd60312c]]` | 0.743 ↑ | 8.34% | Climbing | ~2-3 weeks |\n| `[[model/001b9ef2]]` | 0.750 ↑ | 8.93% | Climbing | ~2-3 weeks |\n| `[[model/2d5307c8]]` | 0.705 ↑ | 9.79% | Climbing | ~3-4 weeks |\n| `[[model/f601bbb5]]` | 0.704 🆕 | 8.93% | NEW | Unknown |\n\n## Recent Changes\n| Date | Portfolio | Model | Action | Reason |\n|------|-----------|-------|--------|--------|\n| 2026-03-12 | — | `[[model/54b33aea]]` | Pipeline update: 4/5 consecutive ≥0.80 | Eval 4 scored 0.8308. One eval from promotion. |\n| 2026-03-12 | — | `[[model/198d0c1f]]`/`[[model/289705b1]]` | Track C restart: 1/5 | Bounced back above 0.80 after reset. Ops increasing. |\n| 2026-03-12 | — | Task attribution correction | `[[model/54b33aea]]` is from `[[task/1d615d47]]` (EXP-14), not `[[task/32062f72]]` (EXP-15) | Analyst correction confirmed via model score task_id. |\n\n## Capacity\n- Available allocation headroom: 100% ($40,000 equity, no models allocated)\n- Models pending promotion: 1 (`[[model/54b33aea]]`, awaiting eval 5 on Mar 13)\n- Next promotion window: Mar 13 ~02:15Z (if 54b33aea ≥0.80 on eval 5)"
  },
  "task-performance": {
    "category": "task-performance",
    "producedBy": "strategist",
    "timestamp": "2026-03-12T09:30:00Z",
    "title": "Task Performance Report",
    "body": "# Task Performance Report\n\n## 🌟 HEADLINE: 54b33aea at 4/5 — One Eval From Promotion! Created EXP-25 (Baseline Scorer + Subgraph Crossover)\n\n`[[model/54b33aea]]` (EXP-14, disabled task) reached **4 consecutive 16w evals ≥0.80** (0.811→0.832→0.833→0.831). **One more eval (~Mar 13 02:15Z) for promotion qualification.** This is the platform's closest-ever approach to production deployment.\n\nEmerging safety models climbing fast: `[[model/001b9ef2]]` (EXP-20) jumped to 0.750 (+2.0pp), `[[model/fd60312c]]` (EXP-17) jumped to 0.743 (+2.5pp). Both on track for 0.80 by Mar 15-17.\n\nCreated `[[task/8ee183d8]]` **EXP-25**: baseline scorer (lowest IS DD) + subgraph crossover (best topology innovation) + NSGA-III. Tests whether combining the safety of EXP-17 with the innovation of EXP-22 produces the ideal model.\n\n## Top Performing Tasks\n\n| Task | Type | Best Fitness | Best Model | Models Produced | Notes |\n|------|------|-------------|------------|-----------------|-------|\n| `[[task/eb61f98b]]` (EXP-22: subgraph-xover) | graph | 0.477 ⚠️ (was 0.818) | `[[model/d6e58262]]` (IS: **0.821** RECORD) | 3 | Highest IS score ever. f601bbb5 IS DD 8.93% ✅. Fitness declining. |\n| `[[task/a72da2ed]]` (EXP-11: GLD tuned) | graph | 0.645 | `[[model/4fc2c04e]]` (**0.855** RECORD, IS DD blocked) | 4 | Record score, rock-solid. IS DD 18.35% blocks promotion. |\n| `[[task/e3017490]]` (EXP-17: feat+baseline) | graph | 0.578 | `[[model/fd60312c]]` (16w: **0.743** ↑, DD **8.34%** ⭐) | 2 | **LOWEST IS DD EVER.** Climbing ~2.5pp/eval. |\n| `[[task/eb1b1e97]]` (EXP-20: pop=300) | graph | 0.455 | `[[model/001b9ef2]]` (16w: **0.750** ↑, DD 8.93% ⭐) | 2 | Climbing ~2.0pp/eval. 103 OOS ops. |\n| `[[task/b1936192]]` (EXP-10: GLD baseline) | graph | 0.640 | `[[model/61694274]]` (IS DD **10.28%** ✅) | 9 | Safety champion. Score fluctuating near 0.80. |\n| `[[task/32062f72]]` (EXP-15: NSGA-III GLD) | graph | 0.510 | `[[model/198d0c1f]]` (16w: 0.797 ❌) | 5 | Former best. All below 0.80 on 16w. |\n| `[[task/8b877f86]]` (EXP-21: DD-weighted) | graph | 0.315 ⚠️ (was 0.544) | `[[model/2d5307c8]]` (16w: 0.683 ↑) | 2 | DD-weighted viable on GLD. Fitness declining. |\n| `[[task/03255fc1]]` (EXP-23: cecpp scorer) | graph | 0.288 | `[[model/3218f580]]` 🆕 (IS DD **7.13%** ⭐⭐⭐ RECORD) | 3 | Record low IS DD! But WR 48%, low exp. Monitoring. |\n| `[[task/880c9eb3]]` (EXP-16: XLE NSGA-III) | graph | 0.243 | `[[model/14064f48]]` (16w: 0.383) | 6 | XLE best (cecpp 0.951, DD 4.36% OOS). |\n| `[[task/4830e9b4]]` (EXP-13: ESTC NSGA-III) | graph | 0.249 | `[[model/64a144a1]]` (~0.534) | 5 | Slowly rising. Deadline Mar 15. |\n| `[[task/b4a94bf2]]` (Baseline: ESTC) | graph | 0.378 | `[[model/ade6e576]]` (~0.537) | 5 | Stable control. |\n\n## Underperforming Tasks\n\n| Task | Type | Avg Score | Common Weakness | Models Produced | Recommendation |\n|------|------|-----------|-----------------|-----------------|----------------|\n| `[[task/98dd3981]]` (EXP-19: AAPL) | graph | 0.263 | Low sharpe (0.27), AAPL -7.43%/month | 1 | ⚠️ Grace period until Mar 14. Likely disable. |\n| `[[task/9ac8eba0]]` (EXP-18: walk-forward) | graph | ~0.465 best | Different model profile. Low IS quality metrics. | 5 | Walk-forward needs more time. Keep monitoring. |\n| `[[task/8269132d]]` (EXP-24: XLE tuned) | graph | 0.282 | Very early | 1 | 🟡 Just started. Give time. |\n\n## Active Experiments\n\n| Task | Hypothesis | Started | Status |\n|------|-----------|---------|--------|\n| `[[task/b4a94bf2]]` Baseline | Control | 2026-02-13 | ✅ Stable. Pop 200/200. |\n| `[[task/b1936192]]` EXP-10 | GLD viable long-short | 2026-02-27 | ✅ 61694274 fluctuating near 0.80. OOS 0.813 stable. |\n| `[[task/a72da2ed]]` EXP-11 | Tuned scorer on GLD | 2026-03-02 | ⭐⭐⭐ 4fc2c04e at 0.855 (RECORD, IS DD blocked). |\n| `[[task/4830e9b4]]` EXP-13 | NSGA-III on ESTC | 2026-03-03 | 🟡 64a144a1 at 0.534. Deadline Mar 15. |\n| `[[task/32062f72]]` EXP-15 | NSGA-III + GLD | 2026-03-06 | ⚠️ All below 0.80 on 16w. Front-loading decay. |\n| `[[task/880c9eb3]]` EXP-16 | XLE diversification | 2026-03-09 | 🟡 6 models, best 0.383. Slow growth. |\n| `[[task/e3017490]]` EXP-17 | Improved features + baseline scorer | 2026-03-10 | ⭐⭐⭐ fd60312c 16w 0.743 ↑. LOWEST IS DD (8.34%). |\n| `[[task/9ac8eba0]]` EXP-18 | Walk-forward optimizer | 2026-03-10 | 🟡 5 models now. Best 16w: 0.465. |\n| `[[task/98dd3981]]` EXP-19 | AAPL diversification | 2026-03-10 | ⚠️ 1 model at 0.263. Grace period Mar 14. |\n| `[[task/eb1b1e97]]` EXP-20 | Larger pop=300, 75 gens | 2026-03-10 | ⭐⭐ 001b9ef2 16w 0.750 ↑. Climbing fast. |\n| `[[task/8b877f86]]` EXP-21 | DD-weighted scorer on GLD | 2026-03-10 | ✅ 2d5307c8 16w 0.683. Fitness declining ⚠️. |\n| `[[task/eb61f98b]]` EXP-22 | Subgraph crossover | 2026-03-10 | ⭐⭐ f601bbb5 IS DD 8.93%. Fitness declining ⚠️. |\n| `[[task/03255fc1]]` EXP-23 | cecpp + smooth_step DD scorer | 2026-03-11 | 🟡 3 models. IS DD 7.13% RECORD. WR 48% concern. |\n| `[[task/8269132d]]` EXP-24 | XLE lower trade_count_factor | 2026-03-11 | 🟡 1 model at 0.282. Very early. |\n| `[[task/8ee183d8]]` EXP-25 🆕 | **Baseline scorer + subgraph crossover + NSGA-III** | **2026-03-12** | 🆕 Just created. First models ~Mar 13-14. |\n\n## Task Optimization Health\n\n| Task | Best Fitness | Pop Size | Errors | Health |\n|------|-------------|----------|--------|--------|\n| `[[task/e3017490]]` EXP-17 | 0.578 | 200/200 | 0 | ✅ Producing |\n| `[[task/eb61f98b]]` EXP-22 | 0.477 ⚠️ | 200/200 | 0 | ⚠️ Fitness declined from 0.818 |\n| `[[task/eb1b1e97]]` EXP-20 | 0.455 | 300/300 | 0 | ✅ Exploring |\n| `[[task/8b877f86]]` EXP-21 | 0.315 ⚠️ | 200/200 | 0 | ⚠️ Fitness declined from 0.544 |\n| `[[task/03255fc1]]` EXP-23 | 0.288 | 200/200 | 0 | ✅ Early |\n| `[[task/8269132d]]` EXP-24 | 0.257 | 200/200 | 0 | ✅ Early |\n| `[[task/9ac8eba0]]` EXP-18 | 0.529 | 200/200 | 0 | ✅ Walk-forward producing |\n| `[[task/98dd3981]]` EXP-19 | 0.247 | 200/200 | 0 | ⚠️ Low fitness (AAPL) |\n| `[[task/880c9eb3]]` EXP-16 | 0.243 | 200/200 | 0 | ✅ XLE growing |\n| `[[task/4830e9b4]]` EXP-13 | 0.249 | 200/200 | 0 | ✅ Low fitness (ESTC) |\n| `[[task/32062f72]]` EXP-15 | 0.510 | 200/200 | 0 | ✅ Healthy |\n| `[[task/b1936192]]` EXP-10 | 0.640 | 200/200 | 0 | ✅ Healthy |\n| `[[task/a72da2ed]]` EXP-11 | 0.645 | 200/200 | 0 | ✅ Recovered |\n| `[[task/b4a94bf2]]` Baseline | 0.378 | 200/200 | 0 | ✅ Stable |\n| `[[task/8ee183d8]]` EXP-25 | — | — | — | 🆕 Just created |\n\n## Key Findings This Cycle\n\n### 1. 🌟 54b33aea at 4/5 Consecutive ≥0.80 — Promotion Imminent\n16w eval trajectory: 0.811 → 0.832 → 0.833 → **0.831**. Slight dip but remains above threshold. ops=61, DD=9.05%, cecpp=0.891, sharpe=11.06. Active trading (49W/2L) sustains score. **One more eval (~Mar 13 02:15Z) for promotion recommendation.**\n\n### 2. 📈 Emerging Safety Models Climbing ~2pp/eval\n- `[[model/001b9ef2]]` (EXP-20): 0.730 → **0.750**. IS DD 8.93%. 103 ops. Active trader. **ETA 0.80: ~Mar 15-16.**\n- `[[model/fd60312c]]` (EXP-17): 0.718 → **0.743**. IS DD 8.34% (safest ever). 62 ops. **ETA 0.80: ~Mar 16-17.**\n\n### 3. 🆕 EXP-23 Sets New IS DD Record: 7.13%\n`[[model/3218f580]]` has IS DD 7.13% with 1923 IS ops. But WR 48.3% and exp $0.65. cecpp scorer may over-optimize for trade frequency.\n\n### 4. 🆕 EXP-25 Created: Best of EXP-17 + EXP-22\nBaseline scorer (lowest IS DD) + subgraph crossover (topology innovation) + NSGA-III.\n\n### 5. ⚠️ EXP-22 and EXP-21 Fitness Declining\nEXP-22: 0.818→0.477. EXP-21: 0.544→0.315. Possible premature convergence. Monitoring.\n\n### 6. Walk-Forward (EXP-18) Producing 5 Models\nDifferent model profile: lower IS DD but poor quality metrics. Best 16w: 0.465. Needs more time.\n\n## Infrastructure\n- **15 active tasks** + 11 disabled = 26 total\n- **~77 workers projected** (14×5 + 1×5 for pop=300)\n- **0 errors across ALL tasks** ✅\n- **4 instruments active:** ESTC, GLD, XLE, AAPL\n\n## Promotion Timeline\n\n| Scenario | Model(s) | Earliest | Probability | Dependency |\n|----------|----------|----------|-------------|------------|\n| **54b33aea holds ≥0.80** | `[[model/54b33aea]]` | **~Mar 13** | **55%** | 1 more eval ≥0.80 (eval 5 on Mar 13 02:15Z). |\n| Emerging safety breakout | `[[model/001b9ef2]]`/`[[model/fd60312c]]` | ~Mar 20+ | **20%** | Need to reach 0.80 + 5 consecutive evals. |\n| No promotion by Mar 16 | — | — | **25%** | 54b33aea drops, others don't reach. |"
  }
}